{"data_mtime":1766640556,"dep_hashes":["74cecd4c679adca2f0dacd1234b59630bfa125a2","d1973c0e9bc3733a5841305c61ece75df2f37dbb"],"dep_lines":[1,1],"dep_prios":[5,5],"dependencies":["numpy.lib._stride_tricks_impl","builtins"],"error_lines":[],"hash":"e2e172cdbc62246980a56d26625a47172ac9d013","id":"numpy.lib.stride_tricks","ignore_all":true,"interface_hash":"dd7027ae8d19d9e47320b73ca2d0347b64ef8656","mtime":1766457515,"options":{"other_options":"2121de79f480fa1cfcd84f3d83993d5dd864dbaa","platform":"win32"},"path":"C:\\Users\\ichirou\\DM_simulation\\.venv\\Lib\\site-packages\\numpy\\lib\\stride_tricks.pyi","plugin_data":null,"size":128,"suppressed":[],"version_id":"1.19.1"}